build123d/__init__.py
build123d/_version.py
build123d/build_common.py
build123d/build_enums.py
build123d/build_line.py
build123d/build_part.py
build123d/build_sketch.py
build123d/drafting.py
build123d/exporters.py
build123d/exporters3d.py
build123d/geometry.py
build123d/importers.py
build123d/joints.py
build123d/jupyter_tools.py
build123d/mesher.py
build123d/objects_curve.py
build123d/objects_part.py
build123d/objects_sketch.py
build123d/operations_generic.py
build123d/operations_part.py
build123d/operations_sketch.py
build123d/pack.py
build123d/persistence.py
build123d/py.typed
build123d/template_render.js
build123d/utils.py
build123d/version.py
build123d/vtk_tools.py
build123d/topology/__init__.py
build123d/topology/composite.py
build123d/topology/constrained_lines.py
build123d/topology/one_d.py
build123d/topology/shape_core.py
build123d/topology/three_d.py
build123d/topology/two_d.py
build123d/topology/utils.py
build123d/topology/zero_d.py
build123d-0.10.0.dist-info/licenses/LICENSE
build123d-0.10.0.dist-info/licenses/NOTICE
build123d-0.10.0.dist-info/METADATA
build123d-0.10.0.dist-info/WHEEL
build123d-0.10.0.dist-info/top_level.txt
build123d-0.10.0.dist-info/RECORD
