Metadata-Version: 2.4
Name: build123d
Version: 0.10.0
Summary: A python CAD programming library
Author-email: Roger Maitland <gumyr9@gmail.com>
License: Apache-2.0
Project-URL: Homepage, https://github.com/gumyr/build123d
Project-URL: Documentation, https://build123d.readthedocs.io/en/latest/index.html
Project-URL: Bug Tracker, https://github.com/gumyr/build123d/issues
Project-URL: Citation, https://doi.org/10.5281/zenodo.14872323
Keywords: 3d models,3d printing,3d,brep,cad,cadquery,opencascade,python
Classifier: License :: OSI Approved :: Apache Software License
Classifier: Operating System :: OS Independent
Classifier: Programming Language :: Python :: 3
Requires-Python: <3.14,>=3.10
License-File: LICENSE
License-File: NOTICE
Requires-Dist: cadquery-ocp<7.9,>=7.8
Requires-Dist: typing_extensions<5,>=4.6.0
Requires-Dist: numpy<3,>=2
Requires-Dist: svgpathtools<2,>=1.5.1
Requires-Dist: anytree<3,>=2.8.0
Requires-Dist: ezdxf<2,>=1.1.0
Requires-Dist: ipython<10,>=8.0.0
Requires-Dist: lib3mf>=2.4.1
Requires-Dist: ocpsvg<0.6,>=0.5
Requires-Dist: ocp_gordon>=0.1.17
Requires-Dist: trianglesolver
Requires-Dist: sympy
Requires-Dist: scipy
Requires-Dist: webcolors~=24.8.0
Provides-Extra: ocp-vscode
Requires-Dist: ocp_vscode; extra == "ocp-vscode"
Provides-Extra: development
Requires-Dist: black; extra == "development"
Requires-Dist: mypy; extra == "development"
Requires-Dist: pylint; extra == "development"
Requires-Dist: pytest; extra == "development"
Requires-Dist: pytest-benchmark; extra == "development"
Requires-Dist: pytest-cov; extra == "development"
Requires-Dist: pytest-xdist; extra == "development"
Requires-Dist: wheel; extra == "development"
Provides-Extra: stubs
Requires-Dist: cadquery-ocp-stubs<7.9,>=7.8; extra == "stubs"
Provides-Extra: docs
Requires-Dist: sphinx==8.1.3; extra == "docs"
Requires-Dist: sphinx-design; extra == "docs"
Requires-Dist: sphinx-copybutton; extra == "docs"
Requires-Dist: sphinx-hoverxref; extra == "docs"
Requires-Dist: sphinx-rtd-theme; extra == "docs"
Requires-Dist: sphinx_autodoc_typehints; extra == "docs"
Provides-Extra: all
Requires-Dist: build123d[ocp_vscode]; extra == "all"
Requires-Dist: build123d[development]; extra == "all"
Requires-Dist: build123d[docs]; extra == "all"
Dynamic: license-file
